Postfix_tools-1.1.1.data/scripts/postresolve
Postfix_tools-1.1.1.data/scripts/tweak_clamav-milter
postscan/__init__.py
postscan/cli.py
postscan/postscan.py
postscan/scanner.py
postscan/state.py
postscan/uuid_helper.py
Postfix_tools-1.1.1.dist-info/LICENSE
Postfix_tools-1.1.1.dist-info/METADATA
Postfix_tools-1.1.1.dist-info/WHEEL
Postfix_tools-1.1.1.dist-info/entry_points.txt
Postfix_tools-1.1.1.dist-info/top_level.txt
Postfix_tools-1.1.1.dist-info/RECORD
