Metadata-Version: 2.1
Name: Postfix-tools
Version: 1.1.1
Summary: Tools, scripts and config for use with the Postfix MTA.
Home-page: https://github.com/unixnut/Postfix-tools
Author: Alastair Irvine
Author-email: alastair@plug.org.au
License: GNU General Public License v3
Keywords: postscan
Platform: UNKNOWN
Classifier: Development Status :: 4 - Beta
Classifier: Intended Audience :: System Administrators
Classifier: License :: OSI Approved :: GNU General Public License v3 (GPLv3)
Classifier: Natural Language :: English
Classifier: Programming Language :: Python :: 2
Classifier: Programming Language :: Python :: 2.7
Classifier: Programming Language :: Python :: 3
Classifier: Programming Language :: Python :: 3.4
Classifier: Programming Language :: Python :: 3.5
Classifier: Programming Language :: Python :: 3.6
Classifier: Programming Language :: Python :: 3.7
Requires-Dist: Click (>=6.0)
